tests/__init__.py
tests/test_pipeline.py
tests_pipeline/README.md
tests_pipeline/__init__.py
tests_pipeline/nodes.py
tests_pipeline/pipeline.py
tests_pipeline/config/parameters.yml
tests_pipeline-0.1.dist-info/METADATA
tests_pipeline-0.1.dist-info/WHEEL
tests_pipeline-0.1.dist-info/top_level.txt
tests_pipeline-0.1.dist-info/RECORD
