Metadata-Version: 2.1
Name: tests-pipeline
Version: 0.1
Summary: Modular pipeline `tests_pipeline`
Home-page: UNKNOWN
Author: UNKNOWN
Author-email: UNKNOWN
License: UNKNOWN
Platform: UNKNOWN
